cloudist/__init__.py
cloudist/meadowrun_session.py
cloudist/plugin.py
cloudist/remote_function.py
pytest_cloudist-0.1.0.dist-info/entry_points.txt
pytest_cloudist-0.1.0.dist-info/LICENSE
pytest_cloudist-0.1.0.dist-info/WHEEL
pytest_cloudist-0.1.0.dist-info/METADATA
pytest_cloudist-0.1.0.dist-info/RECORD
