Metadata-Version: 2.1
Name: pytest-cloudist
Version: 0.1.0
Summary: Distribute tests to cloud machines without fuss
Home-page: https://github.com/kurtschelfthout/pytest-cloudist
License: MIT
Author: Kurt Schelfthout
Author-email: kurt.schelfthout@gmail.com
Requires-Python: >=3.8,<4.0
Classifier: Development Status :: 4 - Beta
Classifier: Framework :: Pytest
Classifier: Intended Audience :: Developers
Classifier: License :: OSI Approved :: MIT License
Classifier: Operating System :: MacOS :: MacOS X
Classifier: Operating System :: Microsoft :: Windows
Classifier: Operating System :: POSIX
Classifier: Programming Language :: Python
Classifier: Programming Language :: Python :: 3
Classifier: Programming Language :: Python :: 3.8
Classifier: Programming Language :: Python :: 3.9
Classifier: Programming Language :: Python :: 3.10
Classifier: Programming Language :: Python :: 3
Classifier: Programming Language :: Python :: 3 :: Only
Classifier: Programming Language :: Python :: 3.10
Classifier: Programming Language :: Python :: 3.8
Classifier: Programming Language :: Python :: 3.9
Classifier: Topic :: Software Development :: Quality Assurance
Classifier: Topic :: Software Development :: Testing
Classifier: Topic :: Utilities
Requires-Dist: meadowrun (>=0.2.4,<0.3.0)
Requires-Dist: pytest (>=7.1.2,<8.0.0)
Project-URL: Repository, https://github.com/kurtschelfthout/pytest-cloudist
